{
  "id": "星虹碎／祭_ev-4",
  "start": 1425081600,
  "end": 1425081600,
  "title": "星虹砕／祭【風】",
  "desc": "星虹碎／祭【风】 于 东京都 下北泽GARDEN 举办",
  "url": "https://thwiki.cc/%E6%98%9F%E8%99%B9%E7%A2%8E%EF%BC%8F%E7%A5%AD#ev-4",
  "type": [
    "LIVE"
  ],
  "color": "#3c3f42",
  "uniqueId": "ff504e3f257c2dab8738c01dfbc5be25e48fa365569369def9ec117040d0734b",
  "location": {
    "type": "google",
    "text": "东京都 下北泽GARDEN",
    "entity": [
      {
        "id": "ChIJzTsuI2vzGGAR4g2vtiN7u5k",
        "addressLine1": "Garden Terrace",
        "addressLine2": "２丁目-３６ 北沢 世田谷区 東京都 日本",
        "provider": "google_places",
        "categories": [
          "premise",
          "geocode"
        ]
      },
      {
        "id": "ChIJm6XsIWvzGGAR3xlUDtWQuuQ",
        "addressLine1": "Garden Terrace下北沢",
        "addressLine2": "日本、東京都世田谷区北沢２丁目３６−１３",
        "provider": "google_places",
        "categories": [
          "premise",
          "geocode"
        ]
      },
      {
        "id": "ChIJfVLfG66OGGAR2THIlzhsvyY",
        "addressLine1": "Garden Eight",
        "addressLine2": "日本、東京都世田谷区北沢３丁目２０−１８",
        "provider": "google_places",
        "categories": [
          "establishment",
          "point_of_interest"
        ]
      },
      {
        "id": "ChIJv6p5LxXzGGARLKg2QeX8KiY",
        "addressLine1": "Garden Kitazawa",
        "addressLine2": "４丁目-１１-２ 北沢 世田谷区 東京都 日本",
        "provider": "google_places",
        "categories": [
          "premise",
          "geocode"
        ]
      },
      {
        "id": "ChIJ_214AOvzGGARPu28knP1nGU",
        "addressLine1": "下北沢GARDEN",
        "addressLine2": "日本、東京都世田谷区北沢１丁目１４−５",
        "provider": "google_places",
        "categories": [
          "establishment",
          "point_of_interest"
        ]
      }
    ]
  },
  "platform": 1
}