{
  "start": 1205020800,
  "end": 1205020800,
  "title": "M3-大阪",
  "desc": "M3-大阪 于 大阪国际会议场 GRAND CUBE OSAKA 举办",
  "url": "https://thwiki.cc/M3#ev-9",
  "type": [
    "展会"
  ],
  "color": "#3c3f42",
  "uniqueId": "d7698b79b7d0c4097e3fce781e783726a522f4089cc0d03e7ae24633f330fdcf",
  "location": {
    "type": "google",
    "text": "大阪国际会议场 GRAND CUBE OSAKA",
    "entity": [
      {
        "id": "ChIJLyAg61jmAGARxD4WxFIVPgw",
        "addressLine1": "大阪府立国際会議場（グランキューブ大阪）",
        "addressLine2": "日本、大阪府大阪市北区中之島５丁目３−５１",
        "provider": "google_places",
        "categories": [
          "establishment",
          "point_of_interest"
        ]
      },
      {
        "id": "ChIJY4tDzFjmAGAR9ptfg7yquZ0",
        "addressLine1": "大阪国際会議場前港",
        "addressLine2": "日本、大阪府大阪市Kita Ward, 中之島５丁目３−６７",
        "provider": "google_places",
        "categories": [
          "establishment",
          "point_of_interest"
        ]
      }
    ]
  },
  "platform": 1,
  "slug": "m3-9"
}