{
  "id": "出行LIVE_ev-7",
  "start": 1280016000,
  "end": 1280016000,
  "title": "おでかけライブ宇都宫142",
  "desc": "出行LIVE 宇都宫142 于 栃木县宇都宫市 宇都宫产业展示馆 举办",
  "url": "https://thwiki.cc/%E5%87%BA%E8%A1%8CLIVE#ev-7",
  "type": [
    "展会"
  ],
  "color": "#3c3f42",
  "uniqueId": "a542e79be9e4c8a9e16cb7d7ead3a7687e7bdb998cbfd19ee826b6c4bf09df78",
  "location": {
    "type": "google",
    "text": "栃木县宇都宫市 宇都宫产业展示馆",
    "entity": [
      {
        "id": "ChIJj__zGWlnH2ARBA7ouCLMoSY",
        "addressLine1": "栃木県宇都宮産業展示館 （マロニエプラザ）",
        "addressLine2": "日本、栃木県宇都宮市元今泉６丁目１−３７",
        "provider": "google_places",
        "categories": [
          "establishment",
          "point_of_interest"
        ]
      }
    ]
  },
  "platform": 1
}