{
  "id": "东方天响录_ev-1",
  "start": 1541894400,
  "end": 1541894400,
  "title": "南航THONLY 东方天响录1",
  "desc": "南航THONLY 东方天响录1 于 南京市 南京航空航天大学 将军路校区 六号楼6402教室 举办",
  "url": "https://thwiki.cc/%E4%B8%9C%E6%96%B9%E5%A4%A9%E5%93%8D%E5%BD%95#ev-1",
  "type": [
    "聚会"
  ],
  "color": "#3c3f42",
  "uniqueId": "68d274546fd7d7e2b8f4ff8be5fb12e19f2cc3e67df26bdfd97388a0f5d6c582",
  "location": {
    "type": "google",
    "text": "南京市 南京航空航天大学 将军路校区 六号楼6402教室",
    "entity": [
      {
        "id": "ChIJbxGANCKPtTURCQCAIN1hKWM",
        "addressLine1": "南京航空航天大学将军路校区",
        "addressLine2": "中華人民共和国 江蘇省 南京市 江寧区 Shengtai West Road",
        "provider": "google_places",
        "categories": [
          "COLLEGE_AND_UNIVERSITY",
          "university",
          "establishment",
          "point_of_interest"
        ]
      }
    ]
  },
  "platform": 1
}