{
  "id": "重庆ComiTime雾都同人祭_ev-10",
  "start": 1392422400,
  "end": 1392422400,
  "title": "ComiTime9",
  "desc": "ComiTime9 于 重庆市 陈家坪展览中心 方馆 2层 举办",
  "url": "https://thwiki.cc/%E9%87%8D%E5%BA%86ComiTime%E9%9B%BE%E9%83%BD%E5%90%8C%E4%BA%BA%E7%A5%AD#ev-10",
  "type": [
    "展会"
  ],
  "color": "#3c3f42",
  "uniqueId": "f62bed67b4bd82ed1441b98a81dae2b295cc41f2a9b5179f17d0ac31adfc07f8",
  "location": {
    "type": "google",
    "text": "重庆市 陈家坪展览中心 方馆 2层",
    "entity": [
      {
        "id": "ChIJ2ybXov7K7DYRnDcY0hAq1cQ",
        "addressLine1": "陈家坪展览中心",
        "addressLine2": "中華人民共和国 重庆市 九竜坡区 高新区 Keyuansi Road",
        "provider": "google_places",
        "categories": [
          "establishment",
          "point_of_interest"
        ]
      }
    ]
  },
  "platform": 1
}