{
  "start": 1599350400,
  "end": 1599350400,
  "title": "超こみっく★トレジャー2020",
  "desc": "超ComicTreasure 2020 于 INTEX大阪 6号馆B 举办",
  "url": "https://thwiki.cc/ComicTreasure#ev-36",
  "type": [
    "展会"
  ],
  "color": "#3c3f42",
  "uniqueId": "91ffbb95b228f380d8908fd6317c7c0074f7030bdc043b3cdc1cb16d91b0a331",
  "location": {
    "type": "google",
    "text": "INTEX大阪 6号馆B",
    "entity": [
      {
        "id": "ChIJ6fHBIE7oAGARy0PQTk2uBtA",
        "addressLine1": "インテックス大阪 6号館",
        "addressLine2": "日本、大阪府大阪市住之江区南港北１丁目５−１０２",
        "provider": "google_places",
        "categories": [
          "establishment",
          "point_of_interest"
        ]
      },
      {
        "id": "ChIJLwzzpPznAGARYnyAmmokYMw",
        "addressLine1": "BEAUTY GENE professional 梅田店",
        "addressLine2": "日本、大阪府大阪市北区茶屋町１３−番",
        "provider": "google_places",
        "categories": [
          "beauty_salon",
          "BEAUTY",
          "establishment",
          "point_of_interest"
        ]
      },
      {
        "id": "ChIJu117ZnPnAGARJ3detj2cBZM",
        "addressLine1": "池島住宅6号館",
        "addressLine2": "日本、大阪府大阪市港区池島２丁目６",
        "provider": "google_places",
        "categories": [
          "establishment",
          "point_of_interest"
        ]
      },
      {
        "id": "ChIJW6aPYxrnAGARCPfbyBD-e9s",
        "addressLine1": "Rakuten mobile Shinsaibashi",
        "addressLine2": "6号 ４丁目-４ 南船場 中央区 大阪市 大阪府 日本",
        "provider": "google_places",
        "categories": [
          "SHOPS_AND_SERVICES",
          "establishment",
          "point_of_interest",
          "store"
        ]
      },
      {
        "id": "ChIJDdnFPBLnAGARN-0FrudqK7c",
        "addressLine1": "船場センタービル６号館",
        "addressLine2": "日本、大阪府大阪市中央区船場中央２丁目３−６",
        "provider": "google_places",
        "categories": [
          "SHOPS_AND_SERVICES",
          "establishment",
          "point_of_interest",
          "store"
        ]
      }
    ]
  },
  "platform": 1,
  "slug": "comictreasure-36"
}