{
  "start": 1564272000,
  "end": 1564272000,
  "title": "东方LiveParty×东方鹏徙谣",
  "desc": "东方LiveParty×东方鹏徙谣 于 深圳 HOU LIVEHOUSE 举办",
  "url": "https://thwiki.cc/%E4%B8%9C%E6%96%B9LiveParty#ev-13",
  "type": [
    "LIVE"
  ],
  "color": "#3c3f42",
  "uniqueId": "d9ae5d5889021e89cf82ba7ff5fd39f47e0575bf402b03beb5f141ba23e9b892",
  "location": {
    "type": "google",
    "text": "深圳 HOU LIVEHOUSE",
    "entity": [
      {
        "id": "ChIJkVLh0Aj0AzQRyYCStw1V7v0",
        "addressLine1": "深圳",
        "addressLine2": "中華人民共和国 広東省",
        "provider": "google_places",
        "categories": [
          "locality",
          "geocode",
          "political"
        ]
      },
      {
        "id": "ChIJR_Xex12NGGAR0ccijxwraxw",
        "addressLine1": "深圳大学東京校",
        "addressLine2": "日本、東京都新宿区四谷１丁目２２−５",
        "provider": "google_places",
        "categories": [
          "COLLEGE_AND_UNIVERSITY",
          "university",
          "establishment",
          "point_of_interest"
        ]
      },
      {
        "id": "ChIJVcsB41oHqDYRmjF_H_mW_9g",
        "addressLine1": "Guangning County, 深圳",
        "addressLine2": "中華人民共和国 広東省 肇慶市",
        "provider": "google_places",
        "categories": [
          "sublocality_level_3",
          "sublocality",
          "geocode",
          "political"
        ]
      },
      {
        "id": "ChIJh00K3D0uaDQRUcaWwX3yDpM",
        "addressLine1": "深圳",
        "addressLine2": "台湾 桃園 Xinwu District",
        "provider": "google_places",
        "categories": [
          "geocode",
          "political",
          "neighborhood"
        ]
      },
      {
        "id": "ChIJqfyG7sf1AzQR6Ri5q3i1424",
        "addressLine1": "深圳书城",
        "addressLine2": "中華人民共和国 広東省 深セン 羅湖区 深南东路",
        "provider": "google_places",
        "categories": [
          "SHOPS_AND_SERVICES",
          "book_store",
          "BOOK_STORE",
          "establishment",
          "point_of_interest",
          "store"
        ]
      }
    ]
  },
  "platform": 1,
  "slug": "东方liveparty-13"
}