{
  "start": 1365206400,
  "end": 1365206400,
  "title": "第二回 コミ×コス",
  "desc": "第二回 COMI×COS 于 大阪市 MERCURY 大阪日本桥店 举办",
  "url": "https://thwiki.cc/COMI%C3%97COS#ev-2",
  "type": [
    "展会"
  ],
  "color": "#3c3f42",
  "uniqueId": "d745d0d48adde044b39e17c4fe903c29c2c23cd76f016d139b890af7d9f80f28",
  "location": {
    "type": "google",
    "text": "大阪市 MERCURY 大阪日本桥店",
    "entity": [
      {
        "id": "ChIJgc5182fnAGARBOdwBHdm1Is",
        "addressLine1": "日本橋",
        "addressLine2": "日本、大阪府大阪市浪速区",
        "provider": "google_places",
        "categories": [
          "sublocality_level_2",
          "sublocality",
          "geocode",
          "political"
        ]
      },
      {
        "id": "ChIJawTe3mnnAGARvBAII1NxMgI",
        "addressLine1": "東京チカラめし 大阪日本橋店",
        "addressLine2": "日本、大阪府大阪市浪速区日本橋３丁目５−２９",
        "provider": "google_places",
        "categories": [
          "restaurant",
          "RESTAURANT",
          "establishment",
          "point_of_interest",
          "FOOD_AND_BEVERAGE",
          "food"
        ]
      },
      {
        "id": "ChIJ9faLPGjnAGARMKfHslQGH2g",
        "addressLine1": "アニメイト 大阪日本橋店",
        "addressLine2": "日本、大阪府大阪市浪速区日本橋西１丁目１−３",
        "provider": "google_places",
        "categories": [
          "MOVIE_RENTAL",
          "SHOPS_AND_SERVICES",
          "book_store",
          "BOOK_STORE",
          "movie_rental",
          "establishment",
          "store",
          "point_of_interest"
        ]
      }
    ]
  },
  "platform": 1,
  "slug": "comi×cos-2"
}