{
  "start": 1448668800,
  "end": 1448668800,
  "title": "T.M.R vol.33",
  "desc": "T.M.R vol.33 于 爱知县名古屋市 club EDITS 举办",
  "url": "https://thwiki.cc/T.M.R#ev-33",
  "type": [
    "夜店舞会"
  ],
  "color": "#3c3f42",
  "uniqueId": "dd37d8aa590cee3d8208652db9dd1cae1781f2fa97cc5dcfdfe71c16ff125635",
  "location": {
    "type": "google",
    "text": "爱知县名古屋市 club EDITS",
    "entity": [
      {
        "id": "ChIJZSN7EJ5wA2ARUrPO6NQilio",
        "addressLine1": "名古屋市",
        "addressLine2": "日本、愛知県",
        "provider": "google_places",
        "categories": [
          "locality",
          "geocode",
          "political"
        ]
      },
      {
        "id": "ChIJO9BXow96A2ARfYheCZ3ya1c",
        "addressLine1": "名古屋市体育館",
        "addressLine2": "日本、愛知県名古屋市熱田区六野２丁目５−３",
        "provider": "google_places",
        "categories": [
          "health",
          "gym",
          "establishment",
          "GYM",
          "point_of_interest",
          "HEALTH_AND_FITNESS"
        ]
      },
      {
        "id": "ChIJD5FhuNBwA2ARhC5UKiCL4Qg",
        "addressLine1": "爱知县美术馆",
        "addressLine2": "日本、愛知県名古屋市東区東桜１丁目１３−２",
        "provider": "google_places",
        "categories": [
          "museum",
          "establishment",
          "point_of_interest",
          "MUSEUM"
        ]
      }
    ]
  },
  "platform": 1,
  "slug": "t.m.r-33"
}