{
  "id": "东方暴莲祭_ev-1",
  "start": 1448668800,
  "end": 1448668800,
  "title": "東方暴蓮祭 VOL.1",
  "desc": "东方暴莲祭 VOL.1 于 广岛市 音魂 举办",
  "url": "https://thwiki.cc/%E4%B8%9C%E6%96%B9%E6%9A%B4%E8%8E%B2%E7%A5%AD#ev-1",
  "type": [
    "夜店舞会"
  ],
  "color": "#3c3f42",
  "uniqueId": "6f70dcf65311f469c9220989a5ccc59079e19628e5444e54975caacd1cefaac7",
  "location": {
    "type": "google",
    "text": "广岛市 音魂",
    "entity": [
      {
        "id": "ChIJeS1OlRqiWjURT9PEFFyce58",
        "addressLine1": "音魂（おんたま）",
        "addressLine2": "日本、広島県広島市中区富士見町１−１",
        "provider": "google_places",
        "categories": [
          "CAFE",
          "cafe",
          "establishment",
          "point_of_interest",
          "FOOD_AND_BEVERAGE",
          "food"
        ]
      }
    ]
  },
  "platform": 1
}