{
  "start": 1561852800,
  "end": 1561852800,
  "title": "東方幻想紅魔祭4",
  "desc": "东方幻想红魔祭4 于 名古屋国际会议场 4号馆 白鸟馆 举办",
  "url": "https://thwiki.cc/%E4%B8%9C%E6%96%B9%E5%B9%BB%E6%83%B3%E7%BA%A2%E9%AD%94%E7%A5%AD#ev-4",
  "type": [
    "展会"
  ],
  "color": "#3c3f42",
  "uniqueId": "2a564768a0628bb965846095213904267063b5770f60b18927333d951ed6efe8",
  "location": {
    "type": "google",
    "text": "名古屋国际会议场 4号馆 白鸟馆",
    "entity": [
      {
        "id": "ChIJIYEgkv55A2ARpuoAd1pQMMg",
        "addressLine1": "名古屋国际会议场",
        "addressLine2": "日本、愛知県名古屋市熱田区熱田西町１−１",
        "provider": "google_places",
        "categories": [
          "establishment",
          "point_of_interest"
        ]
      }
    ]
  },
  "platform": 1,
  "slug": "东方幻想红魔祭-4"
}