{
  "id": "大⑨州东方祭_ev-65",
  "start": 1701561600,
  "end": 1701561600,
  "title": "大⑨州東方祭63",
  "desc": "大⑨州东方祭63 于 佐贺市 656广场 举办",
  "url": "https://thwiki.cc/%E5%A4%A7%E2%91%A8%E5%B7%9E%E4%B8%9C%E6%96%B9%E7%A5%AD#ev-65",
  "type": [
    "展会"
  ],
  "color": "#3c3f42",
  "uniqueId": "de74ca4b077194185d74c79f1c9a42b015d108b54448970a20ae494bb43c99ae",
  "location": {
    "type": "google",
    "text": "佐贺市 656广场",
    "entity": [
      {
        "id": "ChIJk2aksnbKQTURZ8aPb9UBaWY",
        "addressLine1": "656广场",
        "addressLine2": "日本、佐賀県佐賀市呉服元町２−２５",
        "provider": "google_places",
        "categories": [
          "establishment",
          "point_of_interest"
        ]
      }
    ]
  },
  "platform": 1
}